digraph <clinit> {
node [shape=record];
1424788681 [label="L23\lLINENUMBER 425 L23\lLDC \"sun.arch.data.model\"\lINVOKESTATIC java/lang/System.getProperty (Ljava/lang/String;)Ljava/lang/String;\lASTORE 2\lL24\lLINENUMBER 426 L24\lALOAD 2\lIFNULL L25\l"];
205615258 [label="ICONST_1\lGOTO L5\l"];
2108708444 [label="L5\lFRAME SAME1 I\lPUTSTATIC com/sleepycat/je/dbi/MemoryBudget.$assertionsDisabled : Z\lL6\lLINENUMBER 53 L6\lICONST_0\lPUTSTATIC com/sleepycat/je/dbi/MemoryBudget.CLEANUP_DONE : Z\lL7\lLINENUMBER 59 L7\lLDC \"memAdmin\"\lINVOKESTATIC java/lang/Boolean.getBoolean (Ljava/lang/String;)Z\lPUTSTATIC com/sleepycat/je/dbi/MemoryBudget.DEBUG_ADMIN : Z\lL8\lLINENUMBER 60 L8\lLDC \"memLock\"\lINVOKESTATIC java/lang/Boolean.getBoolean (Ljava/lang/String;)Z\lPUTSTATIC com/sleepycat/je/dbi/MemoryBudget.DEBUG_LOCK : Z\lL9\lLINENUMBER 61 L9\lLDC \"memTxn\"\lINVOKESTATIC java/lang/Boolean.getBoolean (Ljava/lang/String;)Z\lPUTSTATIC com/sleepycat/je/dbi/MemoryBudget.DEBUG_TXN : Z\lL10\lLINENUMBER 62 L10\lLDC \"memTreeAdmin\"\lINVOKESTATIC java/lang/Boolean.getBoolean (Ljava/lang/String;)Z\lPUTSTATIC com/sleepycat/je/dbi/MemoryBudget.DEBUG_TREEADMIN : Z\lL11\lLINENUMBER 63 L11\lLDC \"memTree\"\lINVOKESTATIC java/lang/Boolean.getBoolean (Ljava/lang/String;)Z\lPUTSTATIC com/sleepycat/je/dbi/MemoryBudget.DEBUG_TREE : Z\lL12\lLINENUMBER 64 L12\lLDC \"memDOS\"\lINVOKESTATIC java/lang/Boolean.getBoolean (Ljava/lang/String;)Z\lPUTSTATIC com/sleepycat/je/dbi/MemoryBudget.DEBUG_DOS : Z\lL13\lLINENUMBER 345 L13\lICONST_0\lINVOKESTATIC com/sleepycat/je/dbi/MemoryBudget.objectArraySize (I)I\lPUTSTATIC com/sleepycat/je/dbi/MemoryBudget.EMPTY_OBJ_ARRAY : I\lL14\lLINENUMBER 346 L14\lBIPUSH 40\lGETSTATIC com/sleepycat/je/dbi/MemoryBudget.EMPTY_OBJ_ARRAY : I\lISUB\lPUTSTATIC com/sleepycat/je/dbi/MemoryBudget.ARRAYLIST_OVERHEAD_32 : I\lL15\lLINENUMBER 347 L15\lBIPUSH 64\lGETSTATIC com/sleepycat/je/dbi/MemoryBudget.EMPTY_OBJ_ARRAY : I\lISUB\lPUTSTATIC com/sleepycat/je/dbi/MemoryBudget.ARRAYLIST_OVERHEAD_64 : I\lL16\lLINENUMBER 348 L16\lBIPUSH 40\lGETSTATIC com/sleepycat/je/dbi/MemoryBudget.EMPTY_OBJ_ARRAY : I\lISUB\lPUTSTATIC com/sleepycat/je/dbi/MemoryBudget.ARRAYLIST_OVERHEAD_OOPS : I\lL17\lLINENUMBER 415 L17\lICONST_0\lPUTSTATIC com/sleepycat/je/dbi/MemoryBudget.COMPRESSED_OOPS_REQUESTED : Z\lL18\lLINENUMBER 416 L18\lICONST_0\lPUTSTATIC com/sleepycat/je/dbi/MemoryBudget.COMPRESSED_OOPS_KNOWN : Z\lL19\lLINENUMBER 417 L19\lICONST_0\lPUTSTATIC com/sleepycat/je/dbi/MemoryBudget.COMPRESSED_OOPS_KNOWN_ON : Z\lL20\lLINENUMBER 420 L20\lICONST_0\lISTORE 0\lL21\lLINENUMBER 421 L21\lLDC \"je.forceJVMArch\"\lINVOKESTATIC java/lang/System.getProperty (Ljava/lang/String;)Ljava/lang/String;\lASTORE 1\lL0\lLINENUMBER 424 L0\lALOAD 1\lIFNONNULL L22\l"];
517693873 [label="L27\lFRAME APPEND [I java/lang/String java/lang/String]\lICONST_0\l"];
854989361 [label="L30\lFRAME SAME1 I\lISTORE 0\l"];
1725054538 [label="L42\lLINENUMBER 447 L42\lICONST_1\lPUTSTATIC com/sleepycat/je/dbi/MemoryBudget.COMPRESSED_OOPS_REQUESTED : Z\lL43\lLINENUMBER 448 L43\lGOTO L39\l"];
540092563 [label="TRYCATCHBLOCK L0 L1 L2 java/lang/NumberFormatException\lL3\lLINENUMBER 46 L3\lLDC Lcom/sleepycat/je/dbi/MemoryBudget;.class\lINVOKEVIRTUAL java/lang/Class.desiredAssertionStatus ()Z\lIFNE L4\l"];
1428726828 [label="L25\lLINENUMBER 429 L25\lFRAME SAME\lGOTO L1\l"];
1388849499 [label="GETSTATIC com/sleepycat/je/dbi/MemoryBudget.COMPRESSED_OOPS_KNOWN_ON : Z\lGOTO L46\l"];
1392886653 [label="L35\lLINENUMBER 439 L35\lICONST_1\lPUTSTATIC com/sleepycat/je/dbi/MemoryBudget.COMPRESSED_OOPS_KNOWN : Z\lL36\lLINENUMBER 440 L36\lALOAD 2\lINVOKEVIRTUAL java/lang/Boolean.booleanValue ()Z\lPUTSTATIC com/sleepycat/je/dbi/MemoryBudget.COMPRESSED_OOPS_KNOWN_ON : Z\l"];
1037942373 [label="L38\lFRAME APPEND [java/util/List java/util/Iterator]\lALOAD 4\lINVOKEINTERFACE java/util/Iterator.hasNext ()Z\lLDC \"8acc5846-2894-4f50-973f-9442b2a4bb59\"\lINVOKESTATIC edu/cmu/cs/mvelezce/tool/analysis/region/Regions.enter (Ljava/lang/String;)V\lLDC \"8acc5846-2894-4f50-973f-9442b2a4bb59\"\lINVOKESTATIC edu/cmu/cs/mvelezce/tool/analysis/region/Regions.enter (Ljava/lang/String;)V\lLDC \"8acc5846-2894-4f50-973f-9442b2a4bb59\"\lINVOKESTATIC edu/cmu/cs/mvelezce/tool/analysis/region/Regions.enter (Ljava/lang/String;)V\lLDC \"8acc5846-2894-4f50-973f-9442b2a4bb59\"\lINVOKESTATIC edu/cmu/cs/mvelezce/tool/analysis/region/Regions.enter (Ljava/lang/String;)V\lIFEQ L39\l"];
1391119179 [label="L22\lLINENUMBER 430 L22\lFRAME CHOP 1\lALOAD 1\lINVOKESTATIC java/lang/Integer.parseInt (Ljava/lang/String;)I\lBIPUSH 64\lIF_ICMPNE L29\l"];
257718694 [label="L31\lLINENUMBER 437 L31\lFRAME SAME\lINVOKESTATIC com/sleepycat/je/dbi/CompressedOopsDetector.isEnabled ()Ljava/lang/Boolean;\lASTORE 2\lL33\lLINENUMBER 438 L33\lALOAD 2\lIFNULL L34\l"];
1302141801 [label="L45\lFRAME SAME\lGETSTATIC com/sleepycat/je/dbi/MemoryBudget.COMPRESSED_OOPS_REQUESTED : Z\l"];
1824570614 [label="L29\lFRAME SAME\lICONST_0\l"];
1235635586 [label="L39\lFRAME CHOP 1\lLDC \"8acc5846-2894-4f50-973f-9442b2a4bb59\"\lINVOKESTATIC edu/cmu/cs/mvelezce/tool/analysis/region/Regions.exit (Ljava/lang/String;)V\lLDC \"8acc5846-2894-4f50-973f-9442b2a4bb59\"\lINVOKESTATIC edu/cmu/cs/mvelezce/tool/analysis/region/Regions.exit (Ljava/lang/String;)V\lLDC \"8acc5846-2894-4f50-973f-9442b2a4bb59\"\lINVOKESTATIC edu/cmu/cs/mvelezce/tool/analysis/region/Regions.exit (Ljava/lang/String;)V\lLDC \"8acc5846-2894-4f50-973f-9442b2a4bb59\"\lINVOKESTATIC edu/cmu/cs/mvelezce/tool/analysis/region/Regions.exit (Ljava/lang/String;)V\lL44\lLINENUMBER 452 L44\lGETSTATIC com/sleepycat/je/dbi/MemoryBudget.COMPRESSED_OOPS_KNOWN : Z\lIFEQ L45\l"];
1720865719 [label="L2\lLINENUMBER 432 L2\lFRAME SAME1 java/lang/NumberFormatException\lASTORE 2\lL32\lLINENUMBER 433 L32\lALOAD 2\lGETSTATIC java/lang/System.err : Ljava/io/PrintStream;\lINVOKEVIRTUAL java/lang/NumberFormatException.printStackTrace (Ljava/io/PrintStream;)V\l"];
1103132232 [label="L98\lLINENUMBER 622 L98\lFRAME SAME\lLDC 98304\lL197\lLINENUMBER 623 L197\lINVOKESTATIC java/lang/Long.toString (J)Ljava/lang/String;\lPUTSTATIC com/sleepycat/je/dbi/MemoryBudget.MIN_MAX_MEMORY_SIZE_STRING : Ljava/lang/String;\lL198\lLINENUMBER 622 L198\lRETURN\l"];
2008159348 [label="L48\lLINENUMBER 511 L48\lFRAME FULL [I java/lang/String java/lang/Boolean java/util/List I] []\lILOAD 0\lIFEQ L99\l"];
622820646 [label="L46\lFRAME SAME1 I\lISTORE 4\lL47\lLINENUMBER 456 L47\lILOAD 4\lIFEQ L48\l"];
876962272 [label="ALOAD 4\lINVOKEINTERFACE java/util/Iterator.next ()Ljava/lang/Object;\lCHECKCAST java/lang/String\lASTORE 5\lL40\lLINENUMBER 446 L40\lLDC \"-XX:+UseCompressedOops\"\lALOAD 5\lINVOKEVIRTUAL java/lang/String.equals (Ljava/lang/Object;)Z\lIFEQ L41\l"];
1894698434 [label="L4\lFRAME SAME\lICONST_0\l"];
1369468094 [label="L34\lLINENUMBER 444 L34\lFRAME APPEND [java/lang/Boolean]\lINVOKESTATIC java/lang/management/ManagementFactory.getRuntimeMXBean ()Ljava/lang/management/RuntimeMXBean;\lINVOKEINTERFACE java/lang/management/RuntimeMXBean.getInputArguments ()Ljava/util/List;\lASTORE 3\lL37\lLINENUMBER 445 L37\lALOAD 3\lINVOKEINTERFACE java/util/List.iterator ()Ljava/util/Iterator;\lASTORE 4\l"];
1389432760 [label="L49\lLINENUMBER 457 L49\lBIPUSH 24\lPUTSTATIC com/sleepycat/je/dbi/MemoryBudget.LONG_OVERHEAD : I\lL50\lLINENUMBER 458 L50\lBIPUSH 16\lPUTSTATIC com/sleepycat/je/dbi/MemoryBudget.ARRAY_OVERHEAD : I\lL51\lLINENUMBER 459 L51\lICONST_0\lPUTSTATIC com/sleepycat/je/dbi/MemoryBudget.ARRAY_SIZE_INCLUDED : I\lL52\lLINENUMBER 460 L52\lBIPUSH 16\lPUTSTATIC com/sleepycat/je/dbi/MemoryBudget.OBJECT_OVERHEAD : I\lL53\lLINENUMBER 461 L53\lICONST_4\lPUTSTATIC com/sleepycat/je/dbi/MemoryBudget.OBJECT_ARRAY_ITEM_OVERHEAD : I\lL54\lLINENUMBER 462 L54\lBIPUSH 32\lPUTSTATIC com/sleepycat/je/dbi/MemoryBudget.HASHMAP_ENTRY_OVERHEAD : I\lL55\lLINENUMBER 463 L55\lSIPUSH 144\lPUTSTATIC com/sleepycat/je/dbi/MemoryBudget.HASHSET_OVERHEAD : I\lL56\lLINENUMBER 464 L56\lBIPUSH 32\lPUTSTATIC com/sleepycat/je/dbi/MemoryBudget.HASHSET_ENTRY_OVERHEAD : I\lL57\lLINENUMBER 465 L57\lBIPUSH 48\lPUTSTATIC com/sleepycat/je/dbi/MemoryBudget.TREEMAP_OVERHEAD : I\lL58\lLINENUMBER 466 L58\lSIPUSH 1016\lPUTSTATIC com/sleepycat/je/dbi/MemoryBudget.MAPLN_OVERHEAD : I\lL59\lLINENUMBER 467 L59\lSIPUSH 232\lPUTSTATIC com/sleepycat/je/dbi/MemoryBudget.BIN_FIXED_OVERHEAD : I\lL60\lLINENUMBER 468 L60\lBIPUSH 64\lPUTSTATIC com/sleepycat/je/dbi/MemoryBudget.BINDELTA_OVERHEAD : I\lL61\lLINENUMBER 469 L61\lBIPUSH 32\lPUTSTATIC com/sleepycat/je/dbi/MemoryBudget.DELTAINFO_OVERHEAD : I\lL62\lLINENUMBER 470 L62\lBIPUSH 80\lPUTSTATIC com/sleepycat/je/dbi/MemoryBudget.SPARSE_TARGET_ENTRY_OVERHEAD : I\lL63\lLINENUMBER 472 L63\lBIPUSH 16\lPUTSTATIC com/sleepycat/je/dbi/MemoryBudget.DEFAULT_TARGET_ENTRY_OVERHEAD : I\lL64\lLINENUMBER 474 L64\lBIPUSH 16\lPUTSTATIC com/sleepycat/je/dbi/MemoryBudget.DEFAULT_KEYVALS_OVERHEAD : I\lL65\lLINENUMBER 475 L65\lBIPUSH 24\lPUTSTATIC com/sleepycat/je/dbi/MemoryBudget.MAX_KEY_SIZE_KEYVALS_OVERHEAD : I\lL66\lLINENUMBER 477 L66\lBIPUSH 24\lPUTSTATIC com/sleepycat/je/dbi/MemoryBudget.DEFAULT_LONG_REP_OVERHEAD : I\lL67\lLINENUMBER 478 L67\lBIPUSH 24\lPUTSTATIC com/sleepycat/je/dbi/MemoryBudget.SPARSE_LONG_REP_OVERHEAD : I\lL68\lLINENUMBER 479 L68\lBIPUSH 120\lPUTSTATIC com/sleepycat/je/dbi/MemoryBudget.DIN_FIXED_OVERHEAD : I\lL69\lLINENUMBER 480 L69\lSIPUSH 168\lPUTSTATIC com/sleepycat/je/dbi/MemoryBudget.DBIN_FIXED_OVERHEAD : I\lL70\lLINENUMBER 481 L70\lSIPUSH 256\lPUTSTATIC com/sleepycat/je/dbi/MemoryBudget.IN_FIXED_OVERHEAD : I\lL71\lLINENUMBER 482 L71\lSIPUSH 128\lPUTSTATIC com/sleepycat/je/dbi/MemoryBudget.HASHMAP_OVERHEAD : I\lL72\lLINENUMBER 483 L72\lSIPUSH 256\lPUTSTATIC com/sleepycat/je/dbi/MemoryBudget.TWOHASHMAPS_OVERHEAD : I\lL73\lLINENUMBER 484 L73\lBIPUSH 40\lPUTSTATIC com/sleepycat/je/dbi/MemoryBudget.TREEMAP_ENTRY_OVERHEAD : I\lL74\lLINENUMBER 485 L74\lBIPUSH 24\lPUTSTATIC com/sleepycat/je/dbi/MemoryBudget.LN_OVERHEAD : I\lL75\lLINENUMBER 486 L75\lBIPUSH 8\lPUTSTATIC com/sleepycat/je/dbi/MemoryBudget.VERSIONEDLN_OVERHEAD : I\lL76\lLINENUMBER 487 L76\lBIPUSH 40\lPUTSTATIC com/sleepycat/je/dbi/MemoryBudget.DUPCOUNTLN_OVERHEAD : I\lL77\lLINENUMBER 488 L77\lSIPUSH 240\lPUTSTATIC com/sleepycat/je/dbi/MemoryBudget.TXN_OVERHEAD : I\lL78\lLINENUMBER 489 L78\lBIPUSH 80\lPUTSTATIC com/sleepycat/je/dbi/MemoryBudget.CHECKPOINT_REFERENCE_SIZE : I\lL79\lLINENUMBER 490 L79\lBIPUSH 16\lPUTSTATIC com/sleepycat/je/dbi/MemoryBudget.KEY_OVERHEAD : I\lL80\lLINENUMBER 491 L80\lBIPUSH 32\lPUTSTATIC com/sleepycat/je/dbi/MemoryBudget.LOCKIMPL_OVERHEAD : I\lL81\lLINENUMBER 492 L81\lBIPUSH 24\lPUTSTATIC com/sleepycat/je/dbi/MemoryBudget.THINLOCKIMPL_OVERHEAD : I\lL82\lLINENUMBER 493 L82\lBIPUSH 24\lPUTSTATIC com/sleepycat/je/dbi/MemoryBudget.LOCKINFO_OVERHEAD : I\lL83\lLINENUMBER 494 L83\lBIPUSH 56\lPUTSTATIC com/sleepycat/je/dbi/MemoryBudget.WRITE_LOCKINFO_OVERHEAD : I\lL84\lLINENUMBER 495 L84\lBIPUSH 125\lPUTSTATIC com/sleepycat/je/dbi/MemoryBudget.UTILIZATION_PROFILE_ENTRY : I\lL85\lLINENUMBER 496 L85\lBIPUSH 48\lPUTSTATIC com/sleepycat/je/dbi/MemoryBudget.DBFILESUMMARY_OVERHEAD : I\lL86\lLINENUMBER 497 L86\lSIPUSH 464\lPUTSTATIC com/sleepycat/je/dbi/MemoryBudget.TFS_LIST_INITIAL_OVERHEAD : I\lL87\lLINENUMBER 498 L87\lSIPUSH 440\lPUTSTATIC com/sleepycat/je/dbi/MemoryBudget.TFS_LIST_SEGMENT_OVERHEAD : I\lL88\lLINENUMBER 499 L88\lBIPUSH 30\lPUTSTATIC com/sleepycat/je/dbi/MemoryBudget.LN_INFO_OVERHEAD : I\lL89\lLINENUMBER 500 L89\lSIPUSH 128\lPUTSTATIC com/sleepycat/je/dbi/MemoryBudget.FILESUMMARYLN_OVERHEAD : I\lL90\lLINENUMBER 501 L90\lBIPUSH 24\lPUTSTATIC com/sleepycat/je/dbi/MemoryBudget.INENTRY_OVERHEAD : I\lL91\lLINENUMBER 502 L91\lBIPUSH 32\lPUTSTATIC com/sleepycat/je/dbi/MemoryBudget.DELTAINENTRY_OVERHEAD : I\lL92\lLINENUMBER 503 L92\lGETSTATIC com/sleepycat/je/dbi/MemoryBudget.ARRAYLIST_OVERHEAD_OOPS : I\lPUTSTATIC com/sleepycat/je/dbi/MemoryBudget.ARRAYLIST_OVERHEAD : I\lL93\lLINENUMBER 504 L93\lBIPUSH 24\lPUTSTATIC com/sleepycat/je/dbi/MemoryBudget.TUPLE_OUTPUT_OVERHEAD : I\lL94\lLINENUMBER 505 L94\lBIPUSH 48\lPUTSTATIC com/sleepycat/je/dbi/MemoryBudget.DOS_WEAK_BINREF_OVERHEAD : I\lL95\lLINENUMBER 506 L95\lBIPUSH 40\lPUTSTATIC com/sleepycat/je/dbi/MemoryBudget.DOS_OFFHEAP_BINREF_OVERHEAD : I\lL96\lLINENUMBER 507 L96\lBIPUSH 88\lPUTSTATIC com/sleepycat/je/dbi/MemoryBudget.DOS_DEFERRED_LSN_BATCH_OVERHEAD : I\lL97\lLINENUMBER 509 L97\lBIPUSH 16\lPUTSTATIC com/sleepycat/je/dbi/MemoryBudget.DOS_DEFERRED_DELTAREF_OVERHEAD : I\lGOTO L98\l"];
2015261478 [label="L99\lLINENUMBER 565 L99\lFRAME SAME\lBIPUSH 16\lPUTSTATIC com/sleepycat/je/dbi/MemoryBudget.LONG_OVERHEAD : I\lL149\lLINENUMBER 566 L149\lBIPUSH 16\lPUTSTATIC com/sleepycat/je/dbi/MemoryBudget.ARRAY_OVERHEAD : I\lL150\lLINENUMBER 567 L150\lICONST_4\lPUTSTATIC com/sleepycat/je/dbi/MemoryBudget.ARRAY_SIZE_INCLUDED : I\lL151\lLINENUMBER 568 L151\lBIPUSH 8\lPUTSTATIC com/sleepycat/je/dbi/MemoryBudget.OBJECT_OVERHEAD : I\lL152\lLINENUMBER 569 L152\lICONST_4\lPUTSTATIC com/sleepycat/je/dbi/MemoryBudget.OBJECT_ARRAY_ITEM_OVERHEAD : I\lL153\lLINENUMBER 570 L153\lBIPUSH 120\lPUTSTATIC com/sleepycat/je/dbi/MemoryBudget.HASHMAP_OVERHEAD : I\lL154\lLINENUMBER 571 L154\lBIPUSH 24\lPUTSTATIC com/sleepycat/je/dbi/MemoryBudget.HASHMAP_ENTRY_OVERHEAD : I\lL155\lLINENUMBER 572 L155\lSIPUSH 136\lPUTSTATIC com/sleepycat/je/dbi/MemoryBudget.HASHSET_OVERHEAD : I\lL156\lLINENUMBER 573 L156\lBIPUSH 24\lPUTSTATIC com/sleepycat/je/dbi/MemoryBudget.HASHSET_ENTRY_OVERHEAD : I\lL157\lLINENUMBER 574 L157\lSIPUSH 240\lPUTSTATIC com/sleepycat/je/dbi/MemoryBudget.TWOHASHMAPS_OVERHEAD : I\lL158\lLINENUMBER 575 L158\lBIPUSH 48\lPUTSTATIC com/sleepycat/je/dbi/MemoryBudget.TREEMAP_OVERHEAD : I\lL159\lLINENUMBER 576 L159\lSIPUSH 920\lPUTSTATIC com/sleepycat/je/dbi/MemoryBudget.MAPLN_OVERHEAD : I\lL160\lLINENUMBER 577 L160\lBIPUSH 32\lPUTSTATIC com/sleepycat/je/dbi/MemoryBudget.TREEMAP_ENTRY_OVERHEAD : I\lL161\lLINENUMBER 578 L161\lBIPUSH 16\lPUTSTATIC com/sleepycat/je/dbi/MemoryBudget.LN_OVERHEAD : I\lL162\lLINENUMBER 579 L162\lBIPUSH 8\lPUTSTATIC com/sleepycat/je/dbi/MemoryBudget.VERSIONEDLN_OVERHEAD : I\lL163\lLINENUMBER 580 L163\lBIPUSH 32\lPUTSTATIC com/sleepycat/je/dbi/MemoryBudget.DUPCOUNTLN_OVERHEAD : I\lL164\lLINENUMBER 581 L164\lSIPUSH 223\lPUTSTATIC com/sleepycat/je/dbi/MemoryBudget.BIN_FIXED_OVERHEAD : I\lL165\lLINENUMBER 582 L165\lBIPUSH 48\lPUTSTATIC com/sleepycat/je/dbi/MemoryBudget.BINDELTA_OVERHEAD : I\lL166\lLINENUMBER 583 L166\lBIPUSH 24\lPUTSTATIC com/sleepycat/je/dbi/MemoryBudget.DELTAINFO_OVERHEAD : I\lL167\lLINENUMBER 584 L167\lBIPUSH 72\lPUTSTATIC com/sleepycat/je/dbi/MemoryBudget.SPARSE_TARGET_ENTRY_OVERHEAD : I\lL168\lLINENUMBER 585 L168\lBIPUSH 16\lPUTSTATIC com/sleepycat/je/dbi/MemoryBudget.DEFAULT_TARGET_ENTRY_OVERHEAD : I\lL169\lLINENUMBER 587 L169\lBIPUSH 16\lPUTSTATIC com/sleepycat/je/dbi/MemoryBudget.DEFAULT_KEYVALS_OVERHEAD : I\lL170\lLINENUMBER 588 L170\lBIPUSH 16\lPUTSTATIC com/sleepycat/je/dbi/MemoryBudget.MAX_KEY_SIZE_KEYVALS_OVERHEAD : I\lL171\lLINENUMBER 590 L171\lBIPUSH 16\lPUTSTATIC com/sleepycat/je/dbi/MemoryBudget.DEFAULT_LONG_REP_OVERHEAD : I\lL172\lLINENUMBER 591 L172\lBIPUSH 24\lPUTSTATIC com/sleepycat/je/dbi/MemoryBudget.SPARSE_LONG_REP_OVERHEAD : I\lL173\lLINENUMBER 592 L173\lBIPUSH 120\lPUTSTATIC com/sleepycat/je/dbi/MemoryBudget.DIN_FIXED_OVERHEAD : I\lL174\lLINENUMBER 593 L174\lSIPUSH 152\lPUTSTATIC com/sleepycat/je/dbi/MemoryBudget.DBIN_FIXED_OVERHEAD : I\lL175\lLINENUMBER 594 L175\lSIPUSH 248\lPUTSTATIC com/sleepycat/je/dbi/MemoryBudget.IN_FIXED_OVERHEAD : I\lL176\lLINENUMBER 595 L176\lSIPUSH 224\lPUTSTATIC com/sleepycat/je/dbi/MemoryBudget.TXN_OVERHEAD : I\lL177\lLINENUMBER 596 L177\lBIPUSH 64\lPUTSTATIC com/sleepycat/je/dbi/MemoryBudget.CHECKPOINT_REFERENCE_SIZE : I\lL178\lLINENUMBER 597 L178\lBIPUSH 16\lPUTSTATIC com/sleepycat/je/dbi/MemoryBudget.KEY_OVERHEAD : I\lL179\lLINENUMBER 598 L179\lBIPUSH 24\lPUTSTATIC com/sleepycat/je/dbi/MemoryBudget.LOCKIMPL_OVERHEAD : I\lL180\lLINENUMBER 599 L180\lBIPUSH 16\lPUTSTATIC com/sleepycat/je/dbi/MemoryBudget.THINLOCKIMPL_OVERHEAD : I\lL181\lLINENUMBER 600 L181\lBIPUSH 16\lPUTSTATIC com/sleepycat/je/dbi/MemoryBudget.LOCKINFO_OVERHEAD : I\lL182\lLINENUMBER 601 L182\lBIPUSH 48\lPUTSTATIC com/sleepycat/je/dbi/MemoryBudget.WRITE_LOCKINFO_OVERHEAD : I\lL183\lLINENUMBER 602 L183\lBIPUSH 109\lPUTSTATIC com/sleepycat/je/dbi/MemoryBudget.UTILIZATION_PROFILE_ENTRY : I\lL184\lLINENUMBER 603 L184\lBIPUSH 40\lPUTSTATIC com/sleepycat/je/dbi/MemoryBudget.DBFILESUMMARY_OVERHEAD : I\lL185\lLINENUMBER 604 L185\lSIPUSH 464\lPUTSTATIC com/sleepycat/je/dbi/MemoryBudget.TFS_LIST_INITIAL_OVERHEAD : I\lL186\lLINENUMBER 605 L186\lSIPUSH 440\lPUTSTATIC com/sleepycat/je/dbi/MemoryBudget.TFS_LIST_SEGMENT_OVERHEAD : I\lL187\lLINENUMBER 606 L187\lBIPUSH 32\lPUTSTATIC com/sleepycat/je/dbi/MemoryBudget.LN_INFO_OVERHEAD : I\lL188\lLINENUMBER 607 L188\lBIPUSH 112\lPUTSTATIC com/sleepycat/je/dbi/MemoryBudget.FILESUMMARYLN_OVERHEAD : I\lL189\lLINENUMBER 608 L189\lBIPUSH 16\lPUTSTATIC com/sleepycat/je/dbi/MemoryBudget.INENTRY_OVERHEAD : I\lL190\lLINENUMBER 609 L190\lBIPUSH 32\lPUTSTATIC com/sleepycat/je/dbi/MemoryBudget.DELTAINENTRY_OVERHEAD : I\lL191\lLINENUMBER 610 L191\lGETSTATIC com/sleepycat/je/dbi/MemoryBudget.ARRAYLIST_OVERHEAD_32 : I\lPUTSTATIC com/sleepycat/je/dbi/MemoryBudget.ARRAYLIST_OVERHEAD : I\lL192\lLINENUMBER 611 L192\lBIPUSH 24\lPUTSTATIC com/sleepycat/je/dbi/MemoryBudget.TUPLE_OUTPUT_OVERHEAD : I\lL193\lLINENUMBER 612 L193\lBIPUSH 48\lPUTSTATIC com/sleepycat/je/dbi/MemoryBudget.DOS_WEAK_BINREF_OVERHEAD : I\lL194\lLINENUMBER 613 L194\lBIPUSH 32\lPUTSTATIC com/sleepycat/je/dbi/MemoryBudget.DOS_OFFHEAP_BINREF_OVERHEAD : I\lL195\lLINENUMBER 614 L195\lBIPUSH 88\lPUTSTATIC com/sleepycat/je/dbi/MemoryBudget.DOS_DEFERRED_LSN_BATCH_OVERHEAD : I\lL196\lLINENUMBER 616 L196\lBIPUSH 16\lPUTSTATIC com/sleepycat/je/dbi/MemoryBudget.DOS_DEFERRED_DELTAREF_OVERHEAD : I\l"];
710220387 [label="L26\lLINENUMBER 427 L26\lALOAD 2\lINVOKESTATIC java/lang/Integer.parseInt (Ljava/lang/String;)I\lBIPUSH 64\lIF_ICMPNE L27\l"];
917277283 [label="L41\lLINENUMBER 450 L41\lFRAME APPEND [java/lang/String]\lGOTO L38\l"];
535352603 [label="L100\lLINENUMBER 512 L100\lBIPUSH 24\lPUTSTATIC com/sleepycat/je/dbi/MemoryBudget.LONG_OVERHEAD : I\lL101\lLINENUMBER 513 L101\lBIPUSH 24\lPUTSTATIC com/sleepycat/je/dbi/MemoryBudget.ARRAY_OVERHEAD : I\lL102\lLINENUMBER 514 L102\lICONST_0\lPUTSTATIC com/sleepycat/je/dbi/MemoryBudget.ARRAY_SIZE_INCLUDED : I\lL103\lLINENUMBER 515 L103\lBIPUSH 16\lPUTSTATIC com/sleepycat/je/dbi/MemoryBudget.OBJECT_OVERHEAD : I\lL104\lLINENUMBER 516 L104\lBIPUSH 8\lPUTSTATIC com/sleepycat/je/dbi/MemoryBudget.OBJECT_ARRAY_ITEM_OVERHEAD : I\lL105\lLINENUMBER 517 L105\lBIPUSH 52\lPUTSTATIC com/sleepycat/je/dbi/MemoryBudget.HASHMAP_ENTRY_OVERHEAD : I\lL106\lLINENUMBER 518 L106\lSIPUSH 240\lPUTSTATIC com/sleepycat/je/dbi/MemoryBudget.HASHSET_OVERHEAD : I\lL107\lLINENUMBER 519 L107\lBIPUSH 55\lPUTSTATIC com/sleepycat/je/dbi/MemoryBudget.HASHSET_ENTRY_OVERHEAD : I\lL108\lLINENUMBER 520 L108\lBIPUSH 80\lPUTSTATIC com/sleepycat/je/dbi/MemoryBudget.TREEMAP_OVERHEAD : I\lL109\lLINENUMBER 521 L109\lSIPUSH 1624\lPUTSTATIC com/sleepycat/je/dbi/MemoryBudget.MAPLN_OVERHEAD : I\lL110\lLINENUMBER 522 L110\lSIPUSH 352\lPUTSTATIC com/sleepycat/je/dbi/MemoryBudget.BIN_FIXED_OVERHEAD : I\lL111\lLINENUMBER 523 L111\lSIPUSH 176\lPUTSTATIC com/sleepycat/je/dbi/MemoryBudget.DIN_FIXED_OVERHEAD : I\lL112\lLINENUMBER 524 L112\lSIPUSH 232\lPUTSTATIC com/sleepycat/je/dbi/MemoryBudget.DBIN_FIXED_OVERHEAD : I\lL113\lLINENUMBER 525 L113\lSIPUSH 392\lPUTSTATIC com/sleepycat/je/dbi/MemoryBudget.IN_FIXED_OVERHEAD : I\lL114\lLINENUMBER 526 L114\lSIPUSH 219\lPUTSTATIC com/sleepycat/je/dbi/MemoryBudget.HASHMAP_OVERHEAD : I\lL115\lLINENUMBER 527 L115\lSIPUSH 438\lPUTSTATIC com/sleepycat/je/dbi/MemoryBudget.TWOHASHMAPS_OVERHEAD : I\lL116\lLINENUMBER 528 L116\lBIPUSH 72\lPUTSTATIC com/sleepycat/je/dbi/MemoryBudget.BINDELTA_OVERHEAD : I\lL117\lLINENUMBER 529 L117\lBIPUSH 40\lPUTSTATIC com/sleepycat/je/dbi/MemoryBudget.DELTAINFO_OVERHEAD : I\lL118\lLINENUMBER 530 L118\lBIPUSH 120\lPUTSTATIC com/sleepycat/je/dbi/MemoryBudget.SPARSE_TARGET_ENTRY_OVERHEAD : I\lL119\lLINENUMBER 531 L119\lBIPUSH 24\lPUTSTATIC com/sleepycat/je/dbi/MemoryBudget.DEFAULT_TARGET_ENTRY_OVERHEAD : I\lL120\lLINENUMBER 533 L120\lBIPUSH 24\lPUTSTATIC com/sleepycat/je/dbi/MemoryBudget.DEFAULT_KEYVALS_OVERHEAD : I\lL121\lLINENUMBER 534 L121\lBIPUSH 32\lPUTSTATIC com/sleepycat/je/dbi/MemoryBudget.MAX_KEY_SIZE_KEYVALS_OVERHEAD : I\lL122\lLINENUMBER 536 L122\lBIPUSH 32\lPUTSTATIC com/sleepycat/je/dbi/MemoryBudget.DEFAULT_LONG_REP_OVERHEAD : I\lL123\lLINENUMBER 537 L123\lBIPUSH 40\lPUTSTATIC com/sleepycat/je/dbi/MemoryBudget.SPARSE_LONG_REP_OVERHEAD : I\lL124\lLINENUMBER 538 L124\lBIPUSH 64\lPUTSTATIC com/sleepycat/je/dbi/MemoryBudget.TREEMAP_ENTRY_OVERHEAD : I\lL125\lLINENUMBER 539 L125\lBIPUSH 32\lPUTSTATIC com/sleepycat/je/dbi/MemoryBudget.LN_OVERHEAD : I\lL126\lLINENUMBER 540 L126\lBIPUSH 8\lPUTSTATIC com/sleepycat/je/dbi/MemoryBudget.VERSIONEDLN_OVERHEAD : I\lL127\lLINENUMBER 541 L127\lBIPUSH 48\lPUTSTATIC com/sleepycat/je/dbi/MemoryBudget.DUPCOUNTLN_OVERHEAD : I\lL128\lLINENUMBER 542 L128\lSIPUSH 361\lPUTSTATIC com/sleepycat/je/dbi/MemoryBudget.TXN_OVERHEAD : I\lL129\lLINENUMBER 543 L129\lBIPUSH 111\lPUTSTATIC com/sleepycat/je/dbi/MemoryBudget.CHECKPOINT_REFERENCE_SIZE : I\lL130\lLINENUMBER 544 L130\lBIPUSH 24\lPUTSTATIC com/sleepycat/je/dbi/MemoryBudget.KEY_OVERHEAD : I\lL131\lLINENUMBER 545 L131\lBIPUSH 48\lPUTSTATIC com/sleepycat/je/dbi/MemoryBudget.LOCKIMPL_OVERHEAD : I\lL132\lLINENUMBER 546 L132\lBIPUSH 32\lPUTSTATIC com/sleepycat/je/dbi/MemoryBudget.THINLOCKIMPL_OVERHEAD : I\lL133\lLINENUMBER 547 L133\lBIPUSH 32\lPUTSTATIC com/sleepycat/je/dbi/MemoryBudget.LOCKINFO_OVERHEAD : I\lL134\lLINENUMBER 548 L134\lBIPUSH 72\lPUTSTATIC com/sleepycat/je/dbi/MemoryBudget.WRITE_LOCKINFO_OVERHEAD : I\lL135\lLINENUMBER 549 L135\lSIPUSH 160\lPUTSTATIC com/sleepycat/je/dbi/MemoryBudget.UTILIZATION_PROFILE_ENTRY : I\lL136\lLINENUMBER 550 L136\lBIPUSH 48\lPUTSTATIC com/sleepycat/je/dbi/MemoryBudget.DBFILESUMMARY_OVERHEAD : I\lL137\lLINENUMBER 551 L137\lSIPUSH 504\lPUTSTATIC com/sleepycat/je/dbi/MemoryBudget.TFS_LIST_INITIAL_OVERHEAD : I\lL138\lLINENUMBER 552 L138\lSIPUSH 465\lPUTSTATIC com/sleepycat/je/dbi/MemoryBudget.TFS_LIST_SEGMENT_OVERHEAD : I\lL139\lLINENUMBER 553 L139\lBIPUSH 48\lPUTSTATIC com/sleepycat/je/dbi/MemoryBudget.LN_INFO_OVERHEAD : I\lL140\lLINENUMBER 554 L140\lSIPUSH 168\lPUTSTATIC com/sleepycat/je/dbi/MemoryBudget.FILESUMMARYLN_OVERHEAD : I\lL141\lLINENUMBER 555 L141\lBIPUSH 32\lPUTSTATIC com/sleepycat/je/dbi/MemoryBudget.INENTRY_OVERHEAD : I\lL142\lLINENUMBER 556 L142\lBIPUSH 48\lPUTSTATIC com/sleepycat/je/dbi/MemoryBudget.DELTAINENTRY_OVERHEAD : I\lL143\lLINENUMBER 557 L143\lGETSTATIC com/sleepycat/je/dbi/MemoryBudget.ARRAYLIST_OVERHEAD_64 : I\lPUTSTATIC com/sleepycat/je/dbi/MemoryBudget.ARRAYLIST_OVERHEAD : I\lL144\lLINENUMBER 558 L144\lBIPUSH 32\lPUTSTATIC com/sleepycat/je/dbi/MemoryBudget.TUPLE_OUTPUT_OVERHEAD : I\lL145\lLINENUMBER 559 L145\lBIPUSH 72\lPUTSTATIC com/sleepycat/je/dbi/MemoryBudget.DOS_WEAK_BINREF_OVERHEAD : I\lL146\lLINENUMBER 560 L146\lBIPUSH 40\lPUTSTATIC com/sleepycat/je/dbi/MemoryBudget.DOS_OFFHEAP_BINREF_OVERHEAD : I\lL147\lLINENUMBER 561 L147\lSIPUSH 128\lPUTSTATIC com/sleepycat/je/dbi/MemoryBudget.DOS_DEFERRED_LSN_BATCH_OVERHEAD : I\lL148\lLINENUMBER 563 L148\lBIPUSH 24\lPUTSTATIC com/sleepycat/je/dbi/MemoryBudget.DOS_DEFERRED_DELTAREF_OVERHEAD : I\lGOTO L98\l"];
693345846 [label="ICONST_1\lGOTO L30\l"];
247644034 [label="L28\lFRAME SAME1 I\lISTORE 0\l"];
443502884 [label="ICONST_1\lGOTO L28\l"];
214313531 [label="L1\lLINENUMBER 434 L1\lFRAME SAME\lGOTO L31\l"];
entry;
exit;
1424788681 -> 710220387;
1424788681 -> 1428726828;
205615258 -> 2108708444;
2108708444 -> 1424788681;
2108708444 -> 1391119179;
517693873 -> 247644034;
854989361 -> 214313531;
1725054538 -> 1235635586;
540092563 -> 1894698434;
540092563 -> 205615258;
1428726828 -> 214313531;
1388849499 -> 622820646;
1392886653 -> 1369468094;
1037942373 -> 1235635586;
1037942373 -> 876962272;
1391119179 -> 1824570614;
1391119179 -> 693345846;
257718694 -> 1392886653;
257718694 -> 1369468094;
1302141801 -> 622820646;
1824570614 -> 854989361;
1235635586 -> 1302141801;
1235635586 -> 1388849499;
1720865719 -> 257718694;
1103132232 -> exit;
2008159348 -> 2015261478;
2008159348 -> 535352603;
622820646 -> 1389432760;
622820646 -> 2008159348;
entry -> 540092563;
876962272 -> 1725054538;
876962272 -> 917277283;
1894698434 -> 2108708444;
1369468094 -> 1037942373;
1389432760 -> 1103132232;
2015261478 -> 1103132232;
710220387 -> 517693873;
710220387 -> 443502884;
917277283 -> 1037942373;
535352603 -> 1103132232;
693345846 -> 854989361;
247644034 -> 1428726828;
443502884 -> 247644034;
214313531 -> 257718694;
1235635586[fontcolor="purple", penwidth=3, color="purple"];
1037942373[fontcolor="purple", penwidth=3, color="purple"];
}
